suds/__init__.py
suds/argparser.py
suds/builder.py
suds/cache.py
suds/client.py
suds/metrics.py
suds/options.py
suds/plugin.py
suds/properties.py
suds/reader.py
suds/resolver.py
suds/servicedefinition.py
suds/serviceproxy.py
suds/soaparray.py
suds/store.py
suds/sudsobject.py
suds/version.py
suds/wsdl.py
suds/wsse.py
suds/__pycache__/__init__.cpython-37.pyc
suds/__pycache__/argparser.cpython-37.pyc
suds/__pycache__/builder.cpython-37.pyc
suds/__pycache__/cache.cpython-37.pyc
suds/__pycache__/client.cpython-37.pyc
suds/__pycache__/metrics.cpython-37.pyc
suds/__pycache__/options.cpython-37.pyc
suds/__pycache__/plugin.cpython-37.pyc
suds/__pycache__/properties.cpython-37.pyc
suds/__pycache__/reader.cpython-37.pyc
suds/__pycache__/resolver.cpython-37.pyc
suds/__pycache__/servicedefinition.cpython-37.pyc
suds/__pycache__/soaparray.cpython-37.pyc
suds/__pycache__/store.cpython-37.pyc
suds/__pycache__/sudsobject.cpython-37.pyc
suds/__pycache__/version.cpython-37.pyc
suds/__pycache__/wsdl.cpython-37.pyc
suds/__pycache__/wsse.cpython-37.pyc
suds/bindings/__init__.py
suds/bindings/binding.py
suds/bindings/document.py
suds/bindings/multiref.py
suds/bindings/rpc.py
suds/bindings/__pycache__/__init__.cpython-37.pyc
suds/bindings/__pycache__/binding.cpython-37.pyc
suds/bindings/__pycache__/document.cpython-37.pyc
suds/bindings/__pycache__/multiref.cpython-37.pyc
suds/bindings/__pycache__/rpc.cpython-37.pyc
suds/mx/__init__.py
suds/mx/appender.py
suds/mx/basic.py
suds/mx/core.py
suds/mx/encoded.py
suds/mx/literal.py
suds/mx/typer.py
suds/mx/__pycache__/__init__.cpython-37.pyc
suds/mx/__pycache__/appender.cpython-37.pyc
suds/mx/__pycache__/core.cpython-37.pyc
suds/mx/__pycache__/encoded.cpython-37.pyc
suds/mx/__pycache__/literal.cpython-37.pyc
suds/mx/__pycache__/typer.cpython-37.pyc
suds/sax/__init__.py
suds/sax/attribute.py
suds/sax/date.py
suds/sax/document.py
suds/sax/element.py
suds/sax/enc.py
suds/sax/parser.py
suds/sax/text.py
suds/sax/__pycache__/__init__.cpython-37.pyc
suds_community.egg-info/PKG-INFO
suds_community.egg-info/SOURCES.txt
suds_community.egg-info/dependency_links.txt
suds_community.egg-info/top_level.txt
suds_community-0.8.5.dist-info/LICENSE.txt
suds_community-0.8.5.dist-info/METADATA
suds_community-0.8.5.dist-info/WHEEL
suds_community-0.8.5.dist-info/top_level.txt
suds_community-0.8.5.dist-info/RECORD
