Metadata-Version: 2.1
Name: suds-community
Version: 0.8.5
Summary: Lightweight SOAP client (community fork)
Home-page: https://github.com/suds-community/suds
Author: Jeff Ortel
Author-email: jortel@redhat.com
Maintainer: Jurko Gospodnetić
Maintainer-email: jurko.gospodnetic@pke.hr
License: (specified using classifiers)
Download-URL: https://github.com/suds-community/suds/archive/release-0.8.5.tar.gz
Keywords: SOAP,web,service,client
Platform: (specified using classifiers)
Classifier: Development Status :: 5 - Production/Stable
Classifier: Intended Audience :: Developers
Classifier: License :: OSI Approved :: GNU Library or Lesser General Public License (LGPL)
Classifier: Natural Language :: English
Classifier: Operating System :: OS Independent
Classifier: Programming Language :: Python
Classifier: Programming Language :: Python :: 2
Classifier: Programming Language :: Python :: 2.7
Classifier: Programming Language :: Python :: 3
Classifier: Programming Language :: Python :: 3.5
Classifier: Programming Language :: Python :: 3.6
Classifier: Programming Language :: Python :: 3.7
Classifier: Programming Language :: Python :: 3.8
Classifier: Programming Language :: Python :: 3.9
Classifier: Topic :: Internet
Obsoletes: suds
